synq/__init__.py
synq/__main__.py
synq/cli/__init__.py
synq/cli/main.py
synq/cli/commands/__init__.py
synq/cli/commands/generate.py
synq/cli/commands/init.py
synq/cli/commands/migrate.py
synq/cli/commands/status.py
synq/core/__init__.py
synq/core/config.py
synq/core/database.py
synq/core/diff.py
synq/core/migration.py
synq/core/naming.py
synq/core/snapshot.py
synq/utils/__init__.py
synq/utils/import_utils.py
synq/utils/output.py
synq_db-0.0.1.dist-info/METADATA
synq_db-0.0.1.dist-info/WHEEL
synq_db-0.0.1.dist-info/entry_points.txt
synq_db-0.0.1.dist-info/licenses/LICENSE
synq_db-0.0.1.dist-info/RECORD
