Metadata-Version: 2.4
Name: synq-db
Version: 0.0.1
Summary: A modern, snapshot-based database migration tool for SQLAlchemy
Project-URL: Documentation, https://github.com/SudoAI-DEV/Synq#readme
Project-URL: Repository, https://github.com/SudoAI-DEV/Synq
Project-URL: Changelog, https://github.com/SudoAI-DEV/Synq/blob/main/CHANGELOG.md
Author: Synq Contributors
License-Expression: MIT
License-File: LICENSE
Keywords: database,migration,schema,snapshot,sqlalchemy
Classifier: Development Status :: 4 - Beta
Classifier: Environment :: Console
Classifier: Intended Audience :: Developers
Classifier: License :: OSI Approved :: MIT License
Classifier: Operating System :: OS Independent
Classifier: Programming Language :: Python :: 3
Classifier: Programming Language :: Python :: 3.9
Classifier: Programming Language :: Python :: 3.10
Classifier: Programming Language :: Python :: 3.11
Classifier: Programming Language :: Python :: 3.12
Classifier: Programming Language :: Python :: 3.13
Classifier: Topic :: Database
Classifier: Topic :: Software Development :: Libraries :: Python Modules
Classifier: Topic :: System :: Systems Administration
Requires-Python: >=3.9
Requires-Dist: click>=8.0.0
Requires-Dist: sqlalchemy<3.0,>=1.4.0
Requires-Dist: toml>=0.10.0
Requires-Dist: typing-extensions>=4.0.0
Provides-Extra: dev
Requires-Dist: bandit>=1.7.0; extra == 'dev'
Requires-Dist: coverage>=7.0.0; extra == 'dev'
Requires-Dist: mypy>=1.0.0; extra == 'dev'
Requires-Dist: pre-commit>=3.0.0; extra == 'dev'
Requires-Dist: pytest-asyncio>=0.21.0; extra == 'dev'
Requires-Dist: pytest-cov>=4.0.0; extra == 'dev'
Requires-Dist: pytest-mock>=3.10.0; extra == 'dev'
Requires-Dist: pytest>=7.0.0; extra == 'dev'
Requires-Dist: ruff>=0.2.0; extra == 'dev'
Requires-Dist: safety>=2.3.0; extra == 'dev'
Requires-Dist: types-click>=7.0.0; extra == 'dev'
Requires-Dist: types-toml>=0.10.0; extra == 'dev'
Provides-Extra: mysql
Requires-Dist: pymysql>=1.0.0; extra == 'mysql'
Provides-Extra: postgres
Requires-Dist: psycopg2-binary>=2.9.0; extra == 'postgres'
